symplectic/__init__.py
symplectic/_version.py
symplectic/jsonformat.py
symplectic/posts.py
symplectic/render.py
symplectic/rest.py
symplectic/basic/list.html
symplectic/basic/post.html
symplectic/basic/river.html
symplectic-17.11.0.dist-info/DESCRIPTION.rst
symplectic-17.11.0.dist-info/METADATA
symplectic-17.11.0.dist-info/RECORD
symplectic-17.11.0.dist-info/WHEEL
symplectic-17.11.0.dist-info/metadata.json
symplectic-17.11.0.dist-info/top_level.txt
