Metadata-Version: 2.0
Name: symplectic
Version: 17.11.0
Summary: symplectic: generating blogs
Home-page: UNKNOWN
Author: Moshe Zadka
Author-email: zadka.moshe@gmail.com
License: MIT
Platform: UNKNOWN
Requires-Dist: attrs
Requires-Dist: incremental
Requires-Dist: chameleon
